saber/__init__.py
saber/api.py
saber/crypto.py
saber/init.py
saber/utils.py
saber_shad/__init__.py
saber_shad/api.py
saber_shad/crypto.py
saber_shad/utils.py
saber_shad-0.1.0.dist-info/licenses/LICENSE
saber_shad-0.1.0.dist-info/METADATA
saber_shad-0.1.0.dist-info/WHEEL
saber_shad-0.1.0.dist-info/top_level.txt
saber_shad-0.1.0.dist-info/RECORD
