Metadata-Version: 2.4
Name: saber-shad
Version: 0.1.0
Summary: Shad integration library
Author: Mehdi
Author-email: mehdimogdarapi@gmail.com
License: MIT
Requires-Python: >=3.7
License-File: LICENSE
Requires-Dist: requests
Requires-Dist: pycryptodome
Dynamic: author
Dynamic: author-email
Dynamic: license
Dynamic: license-file
Dynamic: requires-dist
Dynamic: requires-python
Dynamic: summary
